langchain_groq-0.3.3.dist-info/METADATA
langchain_groq-0.3.3.dist-info/WHEEL
langchain_groq-0.3.3.dist-info/entry_points.txt
langchain_groq-0.3.3.dist-info/licenses/LICENSE
langchain_groq/__init__.py
langchain_groq/chat_models.py
langchain_groq/py.typed
langchain_groq/version.py
langchain_groq-0.3.3.dist-info/RECORD
