Metadata-Version: 2.1
Name: langchain-groq
Version: 0.3.3
Summary: An integration package connecting Groq and LangChain
License: MIT
Project-URL: Source Code, https://github.com/langchain-ai/langchain/tree/master/libs/partners/groq
Project-URL: Release Notes, https://github.com/langchain-ai/langchain/releases?q=tag%3A%22langchain-groq%3D%3D0%22&expanded=true
Project-URL: repository, https://github.com/langchain-ai/langchain
Requires-Python: >=3.9
Requires-Dist: langchain-core<1.0.0,>=0.3.66
Requires-Dist: groq<1,>=0.4.1
